{
  "android.support.annotation" : [ "AnimRes", "AnimatorRes", "AnyRes", "AnyThread", "ArrayRes", "AttrRes", "BinderThread", "BoolRes", "CallSuper", "CheckResult", "ColorInt", "ColorLong", "ColorRes", "DimenRes", "Dimension", "DrawableRes", "FloatRange", "FractionRes", "HalfFloat", "IdRes", "IntDef", "IntRange", "IntegerRes", "InterpolatorRes", "Keep", "LayoutRes", "MainThread", "MenuRes", "NonNull", "Nullable", "PluralsRes", "Px", "RawRes", "RequiresApi", "RequiresPermission", "RequiresPermission$Read", "RequiresPermission$Write", "RestrictTo", "RestrictTo$Scope", "Size", "StringDef", "StringRes", "StyleRes", "StyleableRes", "TransitionRes", "UiThread", "VisibleForTesting", "WorkerThread", "XmlRes" ],
  "android.support.compat" : [ "BuildConfig" ],
  "android.support.coreui" : [ "BuildConfig" ],
  "android.support.v4.accessibilityservice" : [ "AccessibilityServiceInfoCompat", "AccessibilityServiceInfoCompat$AccessibilityServiceInfoIcsImpl", "AccessibilityServiceInfoCompat$AccessibilityServiceInfoJellyBeanImpl", "AccessibilityServiceInfoCompat$AccessibilityServiceInfoJellyBeanMr2Impl", "AccessibilityServiceInfoCompat$AccessibilityServiceInfoStubImpl", "AccessibilityServiceInfoCompat$AccessibilityServiceInfoVersionImpl", "AccessibilityServiceInfoCompatIcs", "AccessibilityServiceInfoCompatJellyBean", "AccessibilityServiceInfoCompatJellyBeanMr2" ],
  "android.support.v4.app" : [ "ActionBarDrawerToggle", "ActionBarDrawerToggle$ActionBarDrawerToggleImpl", "ActionBarDrawerToggle$ActionBarDrawerToggleImplIcs", "ActionBarDrawerToggle$ActionBarDrawerToggleImplJellybeanMR2", "ActionBarDrawerToggle$Delegate", "ActionBarDrawerToggle$DelegateProvider", "ActionBarDrawerToggle$SlideDrawable", "ActionBarDrawerToggleIcs", "ActionBarDrawerToggleIcs$SetIndicatorInfo", "ActionBarDrawerToggleJellybeanMR2", "ActivityCompat", "ActivityCompat$1", "ActivityCompat$OnRequestPermissionsResultCallback", "ActivityCompat$SharedElementCallback21Impl", "ActivityCompat$SharedElementCallback23Impl", "ActivityCompat$SharedElementCallback23Impl$1", "ActivityCompatApi21", "ActivityCompatApi21$SharedElementCallback21", "ActivityCompatApi21$SharedElementCallbackImpl", "ActivityCompatApi22", "ActivityCompatApi23", "ActivityCompatApi23$OnSharedElementsReadyListenerBridge", "ActivityCompatApi23$RequestPermissionsRequestCodeValidator", "ActivityCompatApi23$SharedElementCallback23", "ActivityCompatApi23$SharedElementCallbackImpl", "ActivityCompatApi23$SharedElementCallbackImpl$1", "ActivityCompatJB", "ActivityManagerCompat", "ActivityManagerCompatKitKat", "ActivityOptionsCompat", "ActivityOptionsCompat$ActivityOptionsImpl21", "ActivityOptionsCompat$ActivityOptionsImpl23", "ActivityOptionsCompat$ActivityOptionsImpl24", "ActivityOptionsCompat$ActivityOptionsImplJB", "ActivityOptionsCompat21", "ActivityOptionsCompat23", "ActivityOptionsCompat24", "ActivityOptionsCompatJB", "AlarmManagerCompat", "AlarmManagerCompatApi21", "AlarmManagerCompatApi23", "AlarmManagerCompatKitKat", "AppOpsManagerCompat", "AppOpsManagerCompat$AppOpsManager23", "AppOpsManagerCompat$AppOpsManagerImpl", "AppOpsManagerCompat23", "BundleCompat", "BundleCompat$BundleCompatBaseImpl", "BundleUtil", "INotificationSideChannel", "INotificationSideChannel$Stub", "INotificationSideChannel$Stub$Proxy", "NotificationBuilderWithActions", "NotificationBuilderWithBuilderAccessor", "NotificationCompat", "NotificationCompat$Action", "NotificationCompat$Action$1", "NotificationCompat$Action$Builder", "NotificationCompat$Action$Extender", "NotificationCompat$Action$WearableExtender", "NotificationCompat$BigPictureStyle", "NotificationCompat$BigTextStyle", "NotificationCompat$Builder", "NotificationCompat$BuilderExtender", "NotificationCompat$CarExtender", "NotificationCompat$CarExtender$UnreadConversation", "NotificationCompat$CarExtender$UnreadConversation$1", "NotificationCompat$CarExtender$UnreadConversation$Builder", "NotificationCompat$Extender", "NotificationCompat$InboxStyle", "NotificationCompat$MessagingStyle", "NotificationCompat$MessagingStyle$Message", "NotificationCompat$NotificationCompatApi16Impl", "NotificationCompat$NotificationCompatApi19Impl", "NotificationCompat$NotificationCompatApi20Impl", "NotificationCompat$NotificationCompatApi21Impl", "NotificationCompat$NotificationCompatApi24Impl", "NotificationCompat$NotificationCompatApi26Impl", "NotificationCompat$NotificationCompatBaseImpl", "NotificationCompat$NotificationCompatBaseImpl$BuilderBase", "NotificationCompat$NotificationCompatImpl", "NotificationCompat$NotificationVisibility", "NotificationCompat$Style", "NotificationCompat$WearableExtender", "NotificationCompatApi20", "NotificationCompatApi20$Builder", "NotificationCompatApi21", "NotificationCompatApi21$Builder", "NotificationCompatApi23", "NotificationCompatApi24", "NotificationCompatApi24$Builder", "NotificationCompatApi26", "NotificationCompatApi26$Builder", "NotificationCompatBase", "NotificationCompatBase$Action", "NotificationCompatBase$Action$Factory", "NotificationCompatBase$UnreadConversation", "NotificationCompatBase$UnreadConversation$Factory", "NotificationCompatExtras", "NotificationCompatJellybean", "NotificationCompatJellybean$Builder", "NotificationCompatKitKat", "NotificationCompatKitKat$Builder", "NotificationCompatSideChannelService", "NotificationCompatSideChannelService$NotificationSideChannelStub", "NotificationManagerCompat", "NotificationManagerCompat$CancelTask", "NotificationManagerCompat$Impl", "NotificationManagerCompat$ImplApi24", "NotificationManagerCompat$ImplBase", "NotificationManagerCompat$ImplKitKat", "NotificationManagerCompat$NotifyTask", "NotificationManagerCompat$ServiceConnectedEvent", "NotificationManagerCompat$SideChannelManager", "NotificationManagerCompat$SideChannelManager$ListenerRecord", "NotificationManagerCompat$Task", "NotificationManagerCompatApi24", "NotificationManagerCompatKitKat", "RemoteInput", "RemoteInput$1", "RemoteInput$Builder", "RemoteInput$Impl", "RemoteInput$ImplApi20", "RemoteInput$ImplBase", "RemoteInput$ImplJellybean", "RemoteInputCompatApi20", "RemoteInputCompatBase", "RemoteInputCompatBase$RemoteInput", "RemoteInputCompatBase$RemoteInput$Factory", "RemoteInputCompatJellybean", "ServiceCompat", "ServiceCompat$Api24ServiceCompatImpl", "ServiceCompat$BaseServiceCompatImpl", "ServiceCompat$ServiceCompatImpl", "ServiceCompat$StopForegroundFlags", "ServiceCompatApi24", "ShareCompat", "ShareCompat$IntentBuilder", "ShareCompat$IntentReader", "ShareCompat$ShareCompatImpl", "ShareCompat$ShareCompatImplBase", "ShareCompat$ShareCompatImplICS", "ShareCompat$ShareCompatImplJB", "ShareCompatICS", "ShareCompatJB", "SharedElementCallback", "SharedElementCallback$OnSharedElementsReadyListener", "SupportActivity", "SupportActivity$ExtraData" ],
  "android.support.v4.content" : [ "ContentResolverCompat", "ContentResolverCompat$ContentResolverCompatImpl", "ContentResolverCompat$ContentResolverCompatImplBase", "ContentResolverCompat$ContentResolverCompatImplJB", "ContentResolverCompatJellybean", "ContextCompat", "IntentCompat", "IntentCompat$IntentCompatApi15Impl", "IntentCompat$IntentCompatBaseImpl", "ModernAsyncTask", "ModernAsyncTask$1", "ModernAsyncTask$2", "ModernAsyncTask$3", "ModernAsyncTask$4", "ModernAsyncTask$AsyncTaskResult", "ModernAsyncTask$InternalHandler", "ModernAsyncTask$Status", "ModernAsyncTask$WorkerRunnable", "ParallelExecutorCompat", "SharedPreferencesCompat", "SharedPreferencesCompat$EditorCompat", "SharedPreferencesCompat$EditorCompat$Helper" ],
  "android.support.v4.content.pm" : [ "ActivityInfoCompat", "ShortcutInfoCompat", "ShortcutInfoCompat$1", "ShortcutInfoCompat$Builder", "ShortcutManagerCompat", "ShortcutManagerCompat$1", "ShortcutManagerCompatApi26" ],
  "android.support.v4.content.res" : [ "ConfigurationHelper", "ConfigurationHelper$1", "ConfigurationHelper$ConfigurationHelperApi17Impl", "ConfigurationHelper$ConfigurationHelperBaseImpl", "ConfigurationHelperJellybeanMr1", "ResourcesCompat", "TypedArrayUtils" ],
  "android.support.v4.database" : [ "DatabaseUtilsCompat" ],
  "android.support.v4.graphics" : [ "BitmapCompat", "BitmapCompat$BitmapCompatApi18Impl", "BitmapCompat$BitmapCompatApi19Impl", "BitmapCompat$BitmapCompatBaseImpl", "PaintCompat", "PaintCompatApi14" ],
  "android.support.v4.graphics.drawable" : [ "DrawableCompat", "DrawableCompat$DrawableCompatApi17Impl", "DrawableCompat$DrawableCompatApi19Impl", "DrawableCompat$DrawableCompatApi21Impl", "DrawableCompat$DrawableCompatApi23Impl", "DrawableCompat$DrawableCompatBaseImpl", "DrawableWrapper", "DrawableWrapperApi14", "DrawableWrapperApi14$DrawableWrapperState", "DrawableWrapperApi14$DrawableWrapperStateBase", "DrawableWrapperApi19", "DrawableWrapperApi19$DrawableWrapperStateKitKat", "DrawableWrapperApi21", "DrawableWrapperApi21$DrawableWrapperStateLollipop", "TintAwareDrawable" ],
  "android.support.v4.hardware.display" : [ "DisplayManagerCompat", "DisplayManagerCompat$JellybeanMr1Impl", "DisplayManagerCompat$LegacyImpl", "DisplayManagerJellybeanMr1" ],
  "android.support.v4.hardware.fingerprint" : [ "FingerprintManagerCompat", "FingerprintManagerCompat$Api23FingerprintManagerCompatImpl", "FingerprintManagerCompat$Api23FingerprintManagerCompatImpl$1", "FingerprintManagerCompat$AuthenticationCallback", "FingerprintManagerCompat$AuthenticationResult", "FingerprintManagerCompat$CryptoObject", "FingerprintManagerCompat$FingerprintManagerCompatImpl", "FingerprintManagerCompat$LegacyFingerprintManagerCompatImpl", "FingerprintManagerCompatApi23", "FingerprintManagerCompatApi23$1", "FingerprintManagerCompatApi23$AuthenticationCallback", "FingerprintManagerCompatApi23$AuthenticationResultInternal", "FingerprintManagerCompatApi23$CryptoObject" ],
  "android.support.v4.internal" : [ "package-info" ],
  "android.support.v4.internal.view" : [ "SupportMenu", "SupportMenuItem", "SupportSubMenu" ],
  "android.support.v4.net" : [ "ConnectivityManagerCompat", "ConnectivityManagerCompat$ConnectivityManagerCompatApi16Impl", "ConnectivityManagerCompat$ConnectivityManagerCompatApi24Impl", "ConnectivityManagerCompat$ConnectivityManagerCompatBaseImpl", "ConnectivityManagerCompat$ConnectivityManagerCompatImpl", "ConnectivityManagerCompat$RestrictBackgroundStatus", "DatagramSocketWrapper", "DatagramSocketWrapper$DatagramSocketImplWrapper", "TrafficStatsCompat", "TrafficStatsCompat$TrafficStatsCompatApi24Impl", "TrafficStatsCompat$TrafficStatsCompatBaseImpl" ],
  "android.support.v4.os" : [ "AsyncTaskCompat", "BuildCompat", "CancellationSignal", "CancellationSignal$OnCancelListener", "CancellationSignalCompatJellybean", "EnvironmentCompat", "EnvironmentCompatKitKat", "IResultReceiver", "IResultReceiver$Stub", "IResultReceiver$Stub$Proxy", "OperationCanceledException", "ParcelableCompat", "ParcelableCompat$CompatCreator", "ParcelableCompatCreatorCallbacks", "ParcelableCompatCreatorHoneycombMR2", "ParcelableCompatCreatorHoneycombMR2Stub", "ResultReceiver", "ResultReceiver$1", "ResultReceiver$MyResultReceiver", "ResultReceiver$MyRunnable", "TraceCompat", "TraceJellybeanMR2", "UserManagerCompat", "UserManagerCompatApi24" ],
  "android.support.v4.text" : [ "ICUCompat", "ICUCompat$ICUCompatApi21Impl", "ICUCompat$ICUCompatBaseImpl", "ICUCompatApi21", "ICUCompatIcs", "TextDirectionHeuristicCompat", "TextDirectionHeuristicsCompat", "TextDirectionHeuristicsCompat$AnyStrong", "TextDirectionHeuristicsCompat$FirstStrong", "TextDirectionHeuristicsCompat$TextDirectionAlgorithm", "TextDirectionHeuristicsCompat$TextDirectionHeuristicImpl", "TextDirectionHeuristicsCompat$TextDirectionHeuristicInternal", "TextDirectionHeuristicsCompat$TextDirectionHeuristicLocale", "TextUtilsCompat", "TextUtilsCompat$TextUtilsCompatImpl", "TextUtilsCompat$TextUtilsCompatJellybeanMr1Impl", "TextUtilsCompatJellybeanMr1" ],
  "android.support.v4.text.util" : [ "LinkifyCompat", "LinkifyCompat$1", "LinkifyCompat$LinkSpec", "LinkifyCompat$LinkifyMask" ],
  "android.support.v4.util" : [ "ArrayMap", "ArrayMap$1", "ArraySet", "ArraySet$1", "AtomicFile", "CircularArray", "CircularIntArray", "ContainerHelpers", "DebugUtils", "LogWriter", "LongSparseArray", "LruCache", "MapCollections", "MapCollections$ArrayIterator", "MapCollections$EntrySet", "MapCollections$KeySet", "MapCollections$MapIterator", "MapCollections$ValuesCollection", "Pair", "PatternsCompat", "Pools", "Pools$Pool", "Pools$SimplePool", "Pools$SynchronizedPool", "Preconditions", "SimpleArrayMap", "SparseArrayCompat", "TimeUtils" ],
  "android.support.v4.view" : [ "AbsSavedState", "AbsSavedState$1", "AbsSavedState$2", "AccessibilityDelegateCompat", "AccessibilityDelegateCompat$AccessibilityDelegateApi16Impl", "AccessibilityDelegateCompat$AccessibilityDelegateApi16Impl$1", "AccessibilityDelegateCompat$AccessibilityDelegateBaseImpl", "AccessibilityDelegateCompat$AccessibilityDelegateBaseImpl$1", "ActionProvider", "ActionProvider$SubUiVisibilityListener", "ActionProvider$VisibilityListener", "AsyncLayoutInflater", "AsyncLayoutInflater$1", "AsyncLayoutInflater$BasicInflater", "AsyncLayoutInflater$InflateRequest", "AsyncLayoutInflater$InflateThread", "AsyncLayoutInflater$OnInflateFinishedListener", "GestureDetectorCompat", "GestureDetectorCompat$GestureDetectorCompatImpl", "GestureDetectorCompat$GestureDetectorCompatImplBase", "GestureDetectorCompat$GestureDetectorCompatImplBase$GestureHandler", "GestureDetectorCompat$GestureDetectorCompatImplJellybeanMr2", "GravityCompat", "GravityCompat$GravityCompatImpl", "GravityCompat$GravityCompatImplBase", "GravityCompat$GravityCompatImplJellybeanMr1", "GravityCompatJellybeanMr1", "InputDeviceCompat", "KeyEventCompat", "LayoutInflaterCompat", "LayoutInflaterCompat$Factory2Wrapper", "LayoutInflaterCompat$LayoutInflaterCompatApi21Impl", "LayoutInflaterCompat$LayoutInflaterCompatBaseImpl", "LayoutInflaterFactory", "MarginLayoutParamsCompat", "MarginLayoutParamsCompat$MarginLayoutParamsCompatImpl", "MarginLayoutParamsCompat$MarginLayoutParamsCompatImplBase", "MarginLayoutParamsCompat$MarginLayoutParamsCompatImplJbMr1", "MarginLayoutParamsCompatJellybeanMr1", "MenuCompat", "MenuItemCompat", "MenuItemCompat$1", "MenuItemCompat$MenuItemCompatApi26Impl", "MenuItemCompat$MenuItemCompatBaseImpl", "MenuItemCompat$MenuVersionImpl", "MenuItemCompat$OnActionExpandListener", "MotionEventCompat", "NestedScrollingChild", "NestedScrollingChildHelper", "NestedScrollingParent", "NestedScrollingParentHelper", "OnApplyWindowInsetsListener", "PagerAdapter", "PagerTabStrip", "PagerTabStrip$1", "PagerTabStrip$2", "PagerTitleStrip", "PagerTitleStrip$PageListener", "PagerTitleStrip$PagerTitleStripImpl", "PagerTitleStrip$PagerTitleStripImplBase", "PagerTitleStrip$PagerTitleStripImplIcs", "PagerTitleStripIcs", "PagerTitleStripIcs$SingleLineAllCapsTransform", "PointerIconCompat", "PointerIconCompat$Api24PointerIconCompatImpl", "PointerIconCompat$BasePointerIconCompatImpl", "PointerIconCompat$PointerIconCompatImpl", "PointerIconCompatApi24", "ScaleGestureDetectorCompat", "ScaleGestureDetectorCompat$BaseScaleGestureDetectorImpl", "ScaleGestureDetectorCompat$ScaleGestureDetectorCompatKitKatImpl", "ScaleGestureDetectorCompat$ScaleGestureDetectorImpl", "ScaleGestureDetectorCompatKitKat", "ScrollingView", "TintableBackgroundView", "VelocityTrackerCompat", "ViewCompat", "ViewCompat$FocusDirection", "ViewCompat$FocusRealDirection", "ViewCompat$FocusRelativeDirection", "ViewCompat$ScrollIndicators", "ViewCompat$ViewCompatApi15Impl", "ViewCompat$ViewCompatApi16Impl", "ViewCompat$ViewCompatApi17Impl", "ViewCompat$ViewCompatApi18Impl", "ViewCompat$ViewCompatApi19Impl", "ViewCompat$ViewCompatApi21Impl", "ViewCompat$ViewCompatApi21Impl$1", "ViewCompat$ViewCompatApi23Impl", "ViewCompat$ViewCompatApi24Impl", "ViewCompat$ViewCompatApi26Impl", "ViewCompat$ViewCompatBaseImpl", "ViewCompatICS", "ViewCompatICS$TooltipHandler", "ViewCompatICS$TooltipHandler$1", "ViewConfigurationCompat", "ViewConfigurationCompat$BaseViewConfigurationVersionImpl", "ViewConfigurationCompat$HoneycombViewConfigurationVersionImpl", "ViewConfigurationCompat$IcsViewConfigurationVersionImpl", "ViewConfigurationCompat$ViewConfigurationVersionImpl", "ViewConfigurationCompatICS", "ViewGroupCompat", "ViewGroupCompat$ViewGroupCompatApi18Impl", "ViewGroupCompat$ViewGroupCompatApi21Impl", "ViewGroupCompat$ViewGroupCompatBaseImpl", "ViewPager", "ViewPager$1", "ViewPager$2", "ViewPager$3", "ViewPager$4", "ViewPager$DecorView", "ViewPager$ItemInfo", "ViewPager$LayoutParams", "ViewPager$MyAccessibilityDelegate", "ViewPager$OnAdapterChangeListener", "ViewPager$OnPageChangeListener", "ViewPager$PageTransformer", "ViewPager$PagerObserver", "ViewPager$SavedState", "ViewPager$SavedState$1", "ViewPager$SimpleOnPageChangeListener", "ViewPager$ViewPositionComparator", "ViewParentCompat", "ViewParentCompat$ViewParentCompatApi19Impl", "ViewParentCompat$ViewParentCompatApi21Impl", "ViewParentCompat$ViewParentCompatBaseImpl", "ViewPropertyAnimatorCompat", "ViewPropertyAnimatorCompat$ViewPropertyAnimatorCompatApi16Impl", "ViewPropertyAnimatorCompat$ViewPropertyAnimatorCompatApi18Impl", "ViewPropertyAnimatorCompat$ViewPropertyAnimatorCompatApi19Impl", "ViewPropertyAnimatorCompat$ViewPropertyAnimatorCompatApi21Impl", "ViewPropertyAnimatorCompat$ViewPropertyAnimatorCompatBaseImpl", "ViewPropertyAnimatorCompat$ViewPropertyAnimatorCompatBaseImpl$MyVpaListener", "ViewPropertyAnimatorCompat$ViewPropertyAnimatorCompatImpl", "ViewPropertyAnimatorCompatICS", "ViewPropertyAnimatorCompatICS$1", "ViewPropertyAnimatorCompatJB", "ViewPropertyAnimatorCompatJB$1", "ViewPropertyAnimatorCompatKK", "ViewPropertyAnimatorCompatKK$1", "ViewPropertyAnimatorListener", "ViewPropertyAnimatorListenerAdapter", "ViewPropertyAnimatorUpdateListener", "WindowCompat", "WindowInsetsCompat", "WindowInsetsCompat$WindowInsetsCompatApi20Impl", "WindowInsetsCompat$WindowInsetsCompatApi21Impl", "WindowInsetsCompat$WindowInsetsCompatBaseImpl", "WindowInsetsCompat$WindowInsetsCompatImpl", "WindowInsetsCompatApi20", "WindowInsetsCompatApi21" ],
  "android.support.v4.view.accessibility" : [ "AccessibilityEventCompat", "AccessibilityEventCompat$AccessibilityEventIcsImpl", "AccessibilityEventCompat$AccessibilityEventJellyBeanImpl", "AccessibilityEventCompat$AccessibilityEventKitKatImpl", "AccessibilityEventCompat$AccessibilityEventStubImpl", "AccessibilityEventCompat$AccessibilityEventVersionImpl", "AccessibilityEventCompatIcs", "AccessibilityEventCompatJellyBean", "AccessibilityEventCompatKitKat", "AccessibilityManagerCompat", "AccessibilityManagerCompat$AccessibilityManagerIcsImpl", "AccessibilityManagerCompat$AccessibilityManagerIcsImpl$1", "AccessibilityManagerCompat$AccessibilityManagerKitKatImpl", "AccessibilityManagerCompat$AccessibilityManagerKitKatImpl$1", "AccessibilityManagerCompat$AccessibilityManagerStubImpl", "AccessibilityManagerCompat$AccessibilityManagerVersionImpl", "AccessibilityManagerCompat$AccessibilityStateChangeListener", "AccessibilityManagerCompat$AccessibilityStateChangeListenerCompat", "AccessibilityManagerCompat$TouchExplorationStateChangeListener", "AccessibilityManagerCompatIcs", "AccessibilityManagerCompatIcs$AccessibilityStateChangeListenerBridge", "AccessibilityManagerCompatIcs$AccessibilityStateChangeListenerWrapper", "AccessibilityManagerCompatKitKat", "AccessibilityManagerCompatKitKat$1", "AccessibilityManagerCompatKitKat$TouchExplorationStateChangeListenerBridge", "AccessibilityManagerCompatKitKat$TouchExplorationStateChangeListenerWrapper", "AccessibilityNodeInfoCompat", "AccessibilityNodeInfoCompat$AccessibilityActionCompat", "AccessibilityNodeInfoCompat$AccessibilityNodeInfoApi21Impl", "AccessibilityNodeInfoCompat$AccessibilityNodeInfoApi22Impl", "AccessibilityNodeInfoCompat$AccessibilityNodeInfoApi23Impl", "AccessibilityNodeInfoCompat$AccessibilityNodeInfoApi24Impl", "AccessibilityNodeInfoCompat$AccessibilityNodeInfoIcsImpl", "AccessibilityNodeInfoCompat$AccessibilityNodeInfoImpl", "AccessibilityNodeInfoCompat$AccessibilityNodeInfoJellybeanImpl", "AccessibilityNodeInfoCompat$AccessibilityNodeInfoJellybeanMr1Impl", "AccessibilityNodeInfoCompat$AccessibilityNodeInfoJellybeanMr2Impl", "AccessibilityNodeInfoCompat$AccessibilityNodeInfoKitKatImpl", "AccessibilityNodeInfoCompat$AccessibilityNodeInfoStubImpl", "AccessibilityNodeInfoCompat$CollectionInfoCompat", "AccessibilityNodeInfoCompat$CollectionItemInfoCompat", "AccessibilityNodeInfoCompat$RangeInfoCompat", "AccessibilityNodeInfoCompatApi21", "AccessibilityNodeInfoCompatApi21$CollectionInfo", "AccessibilityNodeInfoCompatApi21$CollectionItemInfo", "AccessibilityNodeInfoCompatApi22", "AccessibilityNodeInfoCompatApi23", "AccessibilityNodeInfoCompatApi24", "AccessibilityNodeInfoCompatIcs", "AccessibilityNodeInfoCompatJellyBean", "AccessibilityNodeInfoCompatJellybeanMr1", "AccessibilityNodeInfoCompatJellybeanMr2", "AccessibilityNodeInfoCompatKitKat", "AccessibilityNodeInfoCompatKitKat$CollectionInfo", "AccessibilityNodeInfoCompatKitKat$CollectionItemInfo", "AccessibilityNodeInfoCompatKitKat$RangeInfo", "AccessibilityNodeProviderCompat", "AccessibilityNodeProviderCompat$AccessibilityNodeProviderImpl", "AccessibilityNodeProviderCompat$AccessibilityNodeProviderJellyBeanImpl", "AccessibilityNodeProviderCompat$AccessibilityNodeProviderJellyBeanImpl$1", "AccessibilityNodeProviderCompat$AccessibilityNodeProviderKitKatImpl", "AccessibilityNodeProviderCompat$AccessibilityNodeProviderKitKatImpl$1", "AccessibilityNodeProviderCompat$AccessibilityNodeProviderStubImpl", "AccessibilityNodeProviderCompatJellyBean", "AccessibilityNodeProviderCompatJellyBean$1", "AccessibilityNodeProviderCompatJellyBean$AccessibilityNodeInfoBridge", "AccessibilityNodeProviderCompatKitKat", "AccessibilityNodeProviderCompatKitKat$1", "AccessibilityNodeProviderCompatKitKat$AccessibilityNodeInfoBridge", "AccessibilityRecordCompat", "AccessibilityRecordCompat$AccessibilityRecordIcsImpl", "AccessibilityRecordCompat$AccessibilityRecordIcsMr1Impl", "AccessibilityRecordCompat$AccessibilityRecordImpl", "AccessibilityRecordCompat$AccessibilityRecordJellyBeanImpl", "AccessibilityRecordCompat$AccessibilityRecordStubImpl", "AccessibilityRecordCompatIcs", "AccessibilityRecordCompatIcsMr1", "AccessibilityRecordCompatJellyBean", "AccessibilityWindowInfoCompat", "AccessibilityWindowInfoCompat$AccessibilityWindowInfoApi21Impl", "AccessibilityWindowInfoCompat$AccessibilityWindowInfoApi24Impl", "AccessibilityWindowInfoCompat$AccessibilityWindowInfoImpl", "AccessibilityWindowInfoCompat$AccessibilityWindowInfoStubImpl", "AccessibilityWindowInfoCompatApi21", "AccessibilityWindowInfoCompatApi24" ],
  "android.support.v4.view.animation" : [ "FastOutLinearInInterpolator", "FastOutSlowInInterpolator", "LinearOutSlowInInterpolator", "LookupTableInterpolator", "PathInterpolatorApi14", "PathInterpolatorCompat" ],
  "android.support.v4.widget" : [ "AutoScrollHelper", "AutoScrollHelper$ClampedScroller", "AutoScrollHelper$ScrollAnimationRunnable", "CircleImageView", "CircleImageView$OvalShadow", "CompoundButtonCompat", "CompoundButtonCompat$CompoundButtonCompatApi21Impl", "CompoundButtonCompat$CompoundButtonCompatApi23Impl", "CompoundButtonCompat$CompoundButtonCompatBaseImpl", "ContentLoadingProgressBar", "ContentLoadingProgressBar$1", "ContentLoadingProgressBar$2", "CursorAdapter", "CursorAdapter$ChangeObserver", "CursorAdapter$MyDataSetObserver", "CursorFilter", "CursorFilter$CursorFilterClient", "DrawerLayout", "DrawerLayout$AccessibilityDelegate", "DrawerLayout$ChildAccessibilityDelegate", "DrawerLayout$DrawerLayoutCompatImpl", "DrawerLayout$DrawerLayoutCompatImplApi21", "DrawerLayout$DrawerLayoutCompatImplBase", "DrawerLayout$DrawerListener", "DrawerLayout$LayoutParams", "DrawerLayout$SavedState", "DrawerLayout$SavedState$1", "DrawerLayout$SimpleDrawerListener", "DrawerLayout$ViewDragCallback", "DrawerLayout$ViewDragCallback$1", "DrawerLayoutCompatApi21", "DrawerLayoutCompatApi21$InsetsListener", "DrawerLayoutImpl", "EdgeEffectCompat", "EdgeEffectCompat$EdgeEffectApi21Impl", "EdgeEffectCompat$EdgeEffectBaseImpl", "ExploreByTouchHelper", "ExploreByTouchHelper$1", "ExploreByTouchHelper$2", "ExploreByTouchHelper$MyNodeProvider", "FocusStrategy", "FocusStrategy$BoundsAdapter", "FocusStrategy$CollectionAdapter", "FocusStrategy$SequentialComparator", "ListPopupWindowCompat", "ListPopupWindowCompat$BaseListPopupWindowImpl", "ListPopupWindowCompat$KitKatListPopupWindowImpl", "ListPopupWindowCompat$ListPopupWindowImpl", "ListPopupWindowCompatKitKat", "ListViewAutoScrollHelper", "ListViewCompat", "MaterialProgressDrawable", "MaterialProgressDrawable$1", "MaterialProgressDrawable$2", "MaterialProgressDrawable$3", "MaterialProgressDrawable$ProgressDrawableSize", "MaterialProgressDrawable$Ring", "NestedScrollView", "NestedScrollView$AccessibilityDelegate", "NestedScrollView$OnScrollChangeListener", "NestedScrollView$SavedState", "NestedScrollView$SavedState$1", "PopupMenuCompat", "PopupMenuCompat$BasePopupMenuImpl", "PopupMenuCompat$KitKatPopupMenuImpl", "PopupMenuCompat$PopupMenuImpl", "PopupMenuCompatKitKat", "PopupWindowCompat", "PopupWindowCompat$Api21PopupWindowImpl", "PopupWindowCompat$Api23PopupWindowImpl", "PopupWindowCompat$BasePopupWindowImpl", "PopupWindowCompat$KitKatPopupWindowImpl", "PopupWindowCompat$PopupWindowImpl", "PopupWindowCompatApi21", "PopupWindowCompatApi23", "PopupWindowCompatKitKat", "ResourceCursorAdapter", "ScrollerCompat", "SearchViewCompat", "SearchViewCompat$1", "SearchViewCompat$2", "SearchViewCompat$OnCloseListener", "SearchViewCompat$OnCloseListenerCompat", "SearchViewCompat$OnQueryTextListener", "SearchViewCompat$OnQueryTextListenerCompat", "SimpleCursorAdapter", "SimpleCursorAdapter$CursorToStringConverter", "SimpleCursorAdapter$ViewBinder", "SlidingPaneLayout", "SlidingPaneLayout$AccessibilityDelegate", "SlidingPaneLayout$DisableLayerRunnable", "SlidingPaneLayout$DragHelperCallback", "SlidingPaneLayout$LayoutParams", "SlidingPaneLayout$PanelSlideListener", "SlidingPaneLayout$SavedState", "SlidingPaneLayout$SavedState$1", "SlidingPaneLayout$SimplePanelSlideListener", "SlidingPaneLayout$SlidingPanelLayoutImpl", "SlidingPaneLayout$SlidingPanelLayoutImplBase", "SlidingPaneLayout$SlidingPanelLayoutImplJB", "SlidingPaneLayout$SlidingPanelLayoutImplJBMR1", "Space", "SwipeProgressBar", "SwipeRefreshLayout", "SwipeRefreshLayout$1", "SwipeRefreshLayout$2", "SwipeRefreshLayout$3", "SwipeRefreshLayout$4", "SwipeRefreshLayout$5", "SwipeRefreshLayout$6", "SwipeRefreshLayout$7", "SwipeRefreshLayout$8", "SwipeRefreshLayout$OnChildScrollUpCallback", "SwipeRefreshLayout$OnRefreshListener", "TextViewCompat", "TextViewCompat$Api23TextViewCompatImpl", "TextViewCompat$BaseTextViewCompatImpl", "TextViewCompat$JbMr1TextViewCompatImpl", "TextViewCompat$JbMr2TextViewCompatImpl", "TextViewCompat$JbTextViewCompatImpl", "TextViewCompat$TextViewCompatImpl", "TextViewCompatApi23", "TextViewCompatGingerbread", "TextViewCompatJb", "TextViewCompatJbMr1", "TextViewCompatJbMr2", "TintableCompoundButton", "ViewDragHelper", "ViewDragHelper$1", "ViewDragHelper$2", "ViewDragHelper$Callback" ],
  "android.support.v7.recyclerview" : [ "BuildConfig", "R", "R$attr", "R$dimen", "R$id", "R$styleable" ],
  "android.support.v7.util" : [ "AsyncListUtil", "AsyncListUtil$1", "AsyncListUtil$2", "AsyncListUtil$DataCallback", "AsyncListUtil$ViewCallback", "BatchingListUpdateCallback", "DiffUtil", "DiffUtil$1", "DiffUtil$Callback", "DiffUtil$DiffResult", "DiffUtil$DiffResult$1", "DiffUtil$PostponedUpdate", "DiffUtil$Range", "DiffUtil$Snake", "ListUpdateCallback", "MessageThreadUtil", "MessageThreadUtil$1", "MessageThreadUtil$1$1", "MessageThreadUtil$2", "MessageThreadUtil$2$1", "MessageThreadUtil$MessageQueue", "MessageThreadUtil$SyncQueueItem", "SortedList", "SortedList$BatchedCallback", "SortedList$Callback", "ThreadUtil", "ThreadUtil$BackgroundCallback", "ThreadUtil$MainThreadCallback", "TileList", "TileList$Tile" ],
  "android.support.v7.widget" : [ "AdapterHelper", "AdapterHelper$Callback", "AdapterHelper$UpdateOp", "ChildHelper", "ChildHelper$Bucket", "ChildHelper$Callback", "DefaultItemAnimator", "DefaultItemAnimator$1", "DefaultItemAnimator$2", "DefaultItemAnimator$3", "DefaultItemAnimator$4", "DefaultItemAnimator$5", "DefaultItemAnimator$6", "DefaultItemAnimator$7", "DefaultItemAnimator$8", "DefaultItemAnimator$ChangeInfo", "DefaultItemAnimator$MoveInfo", "DividerItemDecoration", "FastScroller", "FastScroller$1", "FastScroller$2", "FastScroller$AnimatorListener", "FastScroller$AnimatorUpdater", "GapWorker", "GapWorker$1", "GapWorker$LayoutPrefetchRegistryImpl", "GapWorker$Task", "GridLayoutManager", "GridLayoutManager$DefaultSpanSizeLookup", "GridLayoutManager$LayoutParams", "GridLayoutManager$SpanSizeLookup", "LayoutState", "LinearLayoutManager", "LinearLayoutManager$AnchorInfo", "LinearLayoutManager$LayoutChunkResult", "LinearLayoutManager$LayoutState", "LinearLayoutManager$SavedState", "LinearLayoutManager$SavedState$1", "LinearSmoothScroller", "LinearSnapHelper", "OpReorderer", "OpReorderer$Callback", "OrientationHelper", "OrientationHelper$1", "OrientationHelper$2", "PagerSnapHelper", "PagerSnapHelper$1", "PositionMap", "PositionMap$ContainerHelpers", "RecyclerView", "RecyclerView$1", "RecyclerView$2", "RecyclerView$3", "RecyclerView$4", "RecyclerView$5", "RecyclerView$6", "RecyclerView$Adapter", "RecyclerView$AdapterDataObservable", "RecyclerView$AdapterDataObserver", "RecyclerView$ChildDrawingOrderCallback", "RecyclerView$ItemAnimator", "RecyclerView$ItemAnimator$AdapterChanges", "RecyclerView$ItemAnimator$ItemAnimatorFinishedListener", "RecyclerView$ItemAnimator$ItemAnimatorListener", "RecyclerView$ItemAnimator$ItemHolderInfo", "RecyclerView$ItemAnimatorRestoreListener", "RecyclerView$ItemDecoration", "RecyclerView$LayoutManager", "RecyclerView$LayoutManager$1", "RecyclerView$LayoutManager$2", "RecyclerView$LayoutManager$LayoutPrefetchRegistry", "RecyclerView$LayoutManager$Properties", "RecyclerView$LayoutParams", "RecyclerView$OnChildAttachStateChangeListener", "RecyclerView$OnFlingListener", "RecyclerView$OnItemTouchListener", "RecyclerView$OnScrollListener", "RecyclerView$RecycledViewPool", "RecyclerView$RecycledViewPool$ScrapData", "RecyclerView$Recycler", "RecyclerView$RecyclerListener", "RecyclerView$RecyclerViewDataObserver", "RecyclerView$SavedState", "RecyclerView$SavedState$1", "RecyclerView$SimpleOnItemTouchListener", "RecyclerView$SmoothScroller", "RecyclerView$SmoothScroller$Action", "RecyclerView$SmoothScroller$ScrollVectorProvider", "RecyclerView$State", "RecyclerView$ViewCacheExtension", "RecyclerView$ViewFlinger", "RecyclerView$ViewHolder", "RecyclerViewAccessibilityDelegate", "RecyclerViewAccessibilityDelegate$ItemDelegate", "ScrollbarHelper", "SimpleItemAnimator", "SnapHelper", "SnapHelper$1", "SnapHelper$2", "StaggeredGridLayoutManager", "StaggeredGridLayoutManager$1", "StaggeredGridLayoutManager$AnchorInfo", "StaggeredGridLayoutManager$LayoutParams", "StaggeredGridLayoutManager$LazySpanLookup", "StaggeredGridLayoutManager$LazySpanLookup$FullSpanItem", "StaggeredGridLayoutManager$LazySpanLookup$FullSpanItem$1", "StaggeredGridLayoutManager$SavedState", "StaggeredGridLayoutManager$SavedState$1", "StaggeredGridLayoutManager$Span", "ViewBoundsCheck", "ViewBoundsCheck$BoundFlags", "ViewBoundsCheck$Callback", "ViewBoundsCheck$ViewBounds", "ViewInfoStore", "ViewInfoStore$InfoRecord", "ViewInfoStore$ProcessCallback" ],
  "android.support.v7.widget.helper" : [ "ItemTouchHelper", "ItemTouchHelper$1", "ItemTouchHelper$2", "ItemTouchHelper$3", "ItemTouchHelper$4", "ItemTouchHelper$5", "ItemTouchHelper$Callback", "ItemTouchHelper$Callback$1", "ItemTouchHelper$Callback$2", "ItemTouchHelper$ItemTouchHelperGestureListener", "ItemTouchHelper$RecoverAnimation", "ItemTouchHelper$RecoverAnimation$1", "ItemTouchHelper$SimpleCallback", "ItemTouchHelper$ViewDropHandler", "ItemTouchUIUtil", "ItemTouchUIUtilImpl", "ItemTouchUIUtilImpl$Gingerbread", "ItemTouchUIUtilImpl$Honeycomb", "ItemTouchUIUtilImpl$Lollipop" ],
  "android.support.v7.widget.util" : [ "SortedListAdapterCallback" ],
  "butterknife" : [ "ButterKnife", "ButterKnife$1", "ButterKnife$Action", "ButterKnife$Finder", "ButterKnife$Finder$1", "ButterKnife$Finder$2", "ButterKnife$Finder$3", "ButterKnife$Setter", "ImmutableViewList", "InjectView", "InjectViews", "OnCheckedChanged", "OnClick", "OnEditorAction", "OnFocusChange", "OnItemClick", "OnItemLongClick", "OnItemSelected", "OnItemSelected$Callback", "OnLongClick", "OnPageChange", "OnPageChange$Callback", "OnTextChanged", "OnTextChanged$Callback", "OnTouch", "Optional" ],
  "butterknife.internal" : [ "Binding", "ButterKnifeProcessor", "CollectionBinding", "CollectionBinding$Kind", "ListenerBinding", "ListenerClass", "ListenerClass$NONE", "ListenerMethod", "Parameter", "ViewBinding", "ViewInjection", "ViewInjector", "ViewInjector$1" ],
  "com.hannesdorfmann.annotatedadapter" : [ "AbsListViewAdapterDelegator", "AbsListViewAnnotatedAdapter", "AbsListViewDelegators", "AutoAbsListViewDelegators", "AutoSupportDelegators", "SimpleAbsListAdapter" ],
  "com.hannesdorfmann.annotatedadapter.annotation" : [ "Field", "ViewField", "ViewType" ],
  "com.hannesdorfmann.annotatedadapter.support.recyclerview" : [ "SupportAnnotatedAdapter", "SupportRecyclerAdapterDelegator", "SupportRecyclerDelegators" ],
  "com.hannesdorfmann.annotatedadaptertest" : [ "BuildConfig", "MainActivity", "MainActivity$$ViewInjector", "MainActivity$$ViewInjector$1", "MainActivity$$ViewInjector$2", "MainActivity$$ViewInjector$3", "MainActivity$$ViewInjector$4", "MainActivity$$ViewInjector$5", "R", "R$attr", "R$dimen", "R$drawable", "R$id", "R$integer", "R$layout", "R$string", "R$style", "R$styleable" ],
  "com.hannesdorfmann.annotatedadaptertest.listview" : [ "GridViewActivity", "GridViewActivity$$ViewInjector", "ListAdapter", "ListAdapterAdapterDelegator", "ListAdapterBinder", "ListAdapterHolders", "ListAdapterHolders$RowMediumViewHolder", "ListAdapterHolders$RowSimpleViewHolder", "ListViewActivity", "ListViewActivity$$ViewInjector" ],
  "com.hannesdorfmann.annotatedadaptertest.listview.inheritance" : [ "AbsColorAdapter", "AbsColorAdapterAdapterDelegator", "AbsColorAdapterBinder", "AbsColorAdapterHolders", "AbsColorAdapterHolders$RowSimpleViewHolder", "ListViewInheritanceActivity", "ListViewInheritanceActivity$$ViewInjector", "ThreeColorsAdapter", "ThreeColorsAdapterAdapterDelegator", "ThreeColorsAdapterBinder", "ThreeColorsAdapterHolders", "ThreeColorsAdapterHolders$RowBigViewHolder", "TwoColorsAdapter", "TwoColorsAdapterAdapterDelegator", "TwoColorsAdapterBinder", "TwoColorsAdapterHolders", "TwoColorsAdapterHolders$RowMediumViewHolder" ],
  "com.hannesdorfmann.annotatedadaptertest.recycler" : [ "DividerItemDecoration", "RecyclerActivity", "RecyclerActivity$$ViewInjector", "RecyclerAdapter", "RecyclerAdapterAdapterDelegator", "RecyclerAdapterBinder", "RecyclerAdapterHolders", "RecyclerAdapterHolders$MediumRowViewHolder", "RecyclerAdapterHolders$RowWithPicViewHolder", "RecyclerAdapterHolders$SmallRowViewHolder" ],
  "com.hannesdorfmann.annotatedadaptertest.recycler.inheritance" : [ "AbsColorAdapter", "AbsColorAdapterAdapterDelegator", "AbsColorAdapterBinder", "AbsColorAdapterHolders", "AbsColorAdapterHolders$SmallRowViewHolder", "ColorActivity", "ColorActivity$$ViewInjector", "DualColorAdapter", "DualColorAdapterAdapterDelegator", "DualColorAdapterBinder", "DualColorAdapterHolders", "DualColorAdapterHolders$MediumRowViewHolder", "ThreeColorAdapter", "ThreeColorAdapterAdapterDelegator", "ThreeColorAdapterBinder", "ThreeColorAdapterHolders", "ThreeColorAdapterHolders$RedRowViewHolder" ]
}